tasking/__init__.py
tasking/scheduler.py
tasking/task.py
tasking/version.py
tasking-1.0.2.dist-info/AUTHORS.rst
tasking-1.0.2.dist-info/LICENSE
tasking-1.0.2.dist-info/METADATA
tasking-1.0.2.dist-info/WHEEL
tasking-1.0.2.dist-info/top_level.txt
tasking-1.0.2.dist-info/RECORD
